resync/__init__.py
resync/archives.py
resync/capability_list.py
resync/change_dump.py
resync/change_dump_manifest.py
resync/change_list.py
resync/client.py
resync/client_state.py
resync/client_utils.py
resync/dump.py
resync/explorer.py
resync/hashes.py
resync/list_base.py
resync/list_base_with_index.py
resync/mapper.py
resync/resource.py
resync/resource_container.py
resync/resource_dump.py
resync/resource_dump_manifest.py
resync/resource_list.py
resync/resource_list_builder.py
resync/resource_set.py
resync/sitemap.py
resync/source_description.py
resync/url_authority.py
resync/url_or_file_open.py
resync/w3c_datetime.py
resync-2.0.1.data/scripts/resync-build
resync-2.0.1.data/scripts/resync-explorer
resync-2.0.1.data/scripts/resync-sync
resync-2.0.1.dist-info/LICENSE.txt
resync-2.0.1.dist-info/METADATA
resync-2.0.1.dist-info/WHEEL
resync-2.0.1.dist-info/top_level.txt
resync-2.0.1.dist-info/RECORD
